KevinCKPytrends/__init__.py
KevinCKPytrends/dailydata.py
KevinCKPytrends/exceptions.py
KevinCKPytrends/request.py
KevinCKPytrends/test_trendReq.py
KevinCKPytrends-0.1.dist-info/METADATA
KevinCKPytrends-0.1.dist-info/WHEEL
KevinCKPytrends-0.1.dist-info/top_level.txt
KevinCKPytrends-0.1.dist-info/RECORD
